composites/__init__.py
composites/core.cp39-win_amd64.pyd
composites/core.pxd
composites/core.pyx
composites/kassapoglou.py
composites/utils.py
composites/version.py
composites-0.8.4.data/data/LICENSE
composites-0.8.4.data/data/README.md
composites-0.8.4.data/data/version.py
composites-0.8.4.dist-info/licenses/LICENSE
composites-0.8.4.dist-info/METADATA
composites-0.8.4.dist-info/WHEEL
composites-0.8.4.dist-info/top_level.txt
composites-0.8.4.dist-info/RECORD
