Metadata-Version: 2.1
Name: composites
Version: 0.8.4
Summary: Methods for analysis and design of composites
Home-page: https://github.com/saullocastro/composites
Author: Saullo G. P. Castro
Author-email: S.G.P.Castro@tudelft.nl
License: 3-Clause BSD
Keywords: mechanics composite materials composites shell classical first-order laminated plate theory
Classifier: Development Status :: 5 - Production/Stable
Classifier: Intended Audience :: Science/Research
Classifier: Intended Audience :: Developers
Classifier: Intended Audience :: Education
Classifier: Intended Audience :: End Users/Desktop
Classifier: Topic :: Scientific/Engineering
Classifier: Topic :: Education
Classifier: Topic :: Software Development
Classifier: Topic :: Software Development :: Libraries :: Python Modules
Classifier: Operating System :: Microsoft :: Windows
Classifier: Operating System :: Unix
Classifier: Operating System :: POSIX :: BSD
Classifier: Programming Language :: Python :: 3.8
Classifier: Programming Language :: Python :: 3.9
Classifier: Programming Language :: Python :: 3.10
Classifier: Programming Language :: Python :: 3.11
Classifier: Programming Language :: Python :: 3.12
Classifier: Programming Language :: Python :: 3.13
Classifier: License :: OSI Approved :: BSD License
License-File: LICENSE
Requires-Dist: numpy
